sourcepp/__init__.py
sourcepp/__init__.pyi
sourcepp/_sourcepp_impl/__init__.pyi
sourcepp/_sourcepp_impl/bsppp.pyi
sourcepp/_sourcepp_impl/gamepp.pyi
sourcepp/_sourcepp_impl/kvpp.pyi
sourcepp/_sourcepp_impl/sourcepp/__init__.pyi
sourcepp/_sourcepp_impl/sourcepp/math.pyi
sourcepp/_sourcepp_impl/steampp.pyi
sourcepp/_sourcepp_impl/toolpp.pyi
sourcepp/_sourcepp_impl/vcryptpp/__init__.pyi
sourcepp/_sourcepp_impl/vcryptpp/VFONT.pyi
sourcepp/_sourcepp_impl/vcryptpp/VICE/__init__.pyi
sourcepp/_sourcepp_impl/vcryptpp/VICE/KnownCodes.pyi
sourcepp/_sourcepp_impl/vpkpp.pyi
sourcepp/_sourcepp_impl/vtfpp/__init__.pyi
sourcepp/_sourcepp_impl/vtfpp/ImageConversion.pyi
sourcepp/_sourcepp_impl/vtfpp/ImageDimensions.pyi
sourcepp/_sourcepp_impl/vtfpp/ImageFormatDetails.pyi
sourcepp/_sourcepp_impl/vtfpp/ImageQuantize.pyi
sourcepp/_sourcepp_impl.cp310-win_amd64.pyd
sourcepp/py.typed
sourcepp-2025.12.4.dist-info/METADATA
sourcepp-2025.12.4.dist-info/WHEEL
sourcepp-2025.12.4.dist-info/licenses/LICENSE
sourcepp-2025.12.4.dist-info/licenses/THIRDPARTY_LEGAL_NOTICES.txt
sourcepp-2025.12.4.dist-info/RECORD
