Metadata-Version: 2.1
Name: sourcepp
Version: 2025.12.4
Summary: Several modern C++20 libraries for sanely parsing Valve formats.
Author-Email: craftablescience <lauralewisdev@gmail.com>
Maintainer-Email: craftablescience <lauralewisdev@gmail.com>
Classifier: License :: OSI Approved :: MIT License
Classifier: Intended Audience :: Developers
Classifier: Topic :: File Formats
Classifier: Programming Language :: C++
Classifier: Programming Language :: Python :: 3 :: Only
Classifier: Programming Language :: Python :: 3.9
Classifier: Programming Language :: Python :: 3.10
Classifier: Programming Language :: Python :: 3.11
Classifier: Programming Language :: Python :: 3.12
Classifier: Programming Language :: Python :: 3.13
Classifier: Programming Language :: Python :: 3.14
Classifier: Programming Language :: Python :: Free Threading
Project-URL: homepage, https://sourcepp.org
Project-URL: repository, https://github.com/craftablescience/sourcepp
Project-URL: issue tracker, https://github.com/craftablescience/sourcepp/issues
Project-URL: funding, https://ko-fi.com/craftablescience
Requires-Python: >=3.9
